modzy/__init__.py
modzy/_api_object.py
modzy/_size.py
modzy/_util.py
modzy/client.py
modzy/error.py
modzy/http.py
modzy/jobs.py
modzy/models.py
modzy/results.py
modzy/tags.py
modzy/edge/__init__.py
modzy/edge/client.py
modzy/edge/inferences.py
modzy/edge/jobs.py
modzy/edge/proto/__init__.py
modzy/edge/proto/accounting/__init__.py
modzy/edge/proto/accounting/v1/__init__.py
modzy/edge/proto/accounting/v1/accounting_pb2.py
modzy/edge/proto/accounting/v1/accounting_pb2.pyi
modzy/edge/proto/common/__init__.py
modzy/edge/proto/common/v1/__init__.py
modzy/edge/proto/common/v1/common_pb2.py
modzy/edge/proto/common/v1/common_pb2.pyi
modzy/edge/proto/common/v1/common_pb2_grpc.py
modzy/edge/proto/common/v1/errors_pb2.py
modzy/edge/proto/common/v1/errors_pb2.pyi
modzy/edge/proto/inferences/__init__.py
modzy/edge/proto/inferences/api/__init__.py
modzy/edge/proto/inferences/api/v1/__init__.py
modzy/edge/proto/inferences/api/v1/inferences_pb2.py
modzy/edge/proto/inferences/api/v1/inferences_pb2.pyi
modzy/edge/proto/inferences/api/v1/inferences_pb2_grpc.py
modzy/edge/proto/jobs/__init__.py
modzy/edge/proto/jobs/v1/__init__.py
modzy/edge/proto/jobs/v1/job_pb2.py
modzy/edge/proto/jobs/v1/job_pb2_grpc.py
modzy/edge/proto/jobs/v1/jobs_pb2.py
modzy/edge/proto/jobs/v1/jobs_pb2.pyi
modzy/edge/proto/jobs/v1/jobs_pb2_grpc.py
modzy/edge/proto/protoc_gen_openapiv2/__init__.py
modzy/edge/proto/protoc_gen_openapiv2/options/__init__.py
modzy/edge/proto/protoc_gen_openapiv2/options/annotations_pb2.py
modzy/edge/proto/protoc_gen_openapiv2/options/annotations_pb2_grpc.py
modzy/edge/proto/protoc_gen_openapiv2/options/openapiv2_pb2.py
modzy/edge/proto/protoc_gen_openapiv2/options/openapiv2_pb2_grpc.py
modzy/edge/proto/results/__init__.py
modzy/edge/proto/results/v1/__init__.py
modzy/edge/proto/results/v1/results_pb2.py
modzy/edge/proto/results/v1/results_pb2_grpc.py
samples/__init__.py
samples/job_with_aws_input_sample.py
samples/job_with_embedded_input_sample.py
modzy_sdk-0.11.6.dist-info/LICENSE
modzy_sdk-0.11.6.dist-info/METADATA
modzy_sdk-0.11.6.dist-info/WHEEL
modzy_sdk-0.11.6.dist-info/top_level.txt
modzy_sdk-0.11.6.dist-info/RECORD
