Metadata-Version: 2.1
Name: modzy-sdk
Version: 0.11.6
Summary: Modzy's Python SDK queries and deploys models, submits inference jobs and returns results directly to your editor.
Home-page: https://github.com/modzy/sdk-python
Author: Modzy
Author-email: support@modzy.com
License: UNKNOWN
Keywords: modzy,sdk
Platform: UNKNOWN
Classifier: Development Status :: 2 - Pre-Alpha
Classifier: Intended Audience :: Developers
Classifier: Natural Language :: English
Classifier: Programming Language :: Python :: 3
Classifier: Programming Language :: Python :: 3.4
Classifier: Programming Language :: Python :: 3.5
Classifier: Programming Language :: Python :: 3.6
Classifier: Programming Language :: Python :: 3.7
Requires-Python: >=3.7
License-File: LICENSE
Requires-Dist: requests
Requires-Dist: python-dotenv
Requires-Dist: deprecation
Requires-Dist: protobuf ~=4.21.10
Requires-Dist: grpcio
Requires-Dist: google-api-python-client
Requires-Dist: boto3
